{
  "project_info": {
    "project_number": "211815677080",
    "project_id": "electrum-ahmad",
    "storage_bucket": "electrum-ahmad.firebasestorage.app"
  },
  "client": [
    {
      "client_info": {
        "mobilesdk_app_id": "1:211815677080:android:4c35f6c3ce28d099a464ed",
        "android_client_info": {
          "package_name": "com.electrum.ahmad.electrum_ahmad"
        }
      },
      "oauth_client": [],
      "api_key": [
        {
          "current_key": "AIzaSyAZU_PCny2YfHe0btsiIL82P8B4gYxF-fk"
        }
      ],
      "services": {
        "appinvite_service": {
          "other_platform_oauth_client": []
        }
      }
    }
  ],
  "configuration_version": "1"
}